VSTLight/__init__.py
VSTLight/channel.py
VSTLight/network_controller.py
VSTLight/utils.py
vstlight-1.0.0.dist-info/METADATA
vstlight-1.0.0.dist-info/WHEEL
vstlight-1.0.0.dist-info/licenses/LICENSE
vstlight-1.0.0.dist-info/RECORD
