Metadata-Version: 2.3
Name: VSTLight
Version: 1.0.0
Summary: Python package for seamless control of network-compatible VLP light controllers from VS Technology.
Project-URL: Homepage, https://github.com/Attrup/VST-Light
Author-email: Jonas Attrup <attrup.jonas@gmail.com>
License: MIT License
License-File: LICENSE
Classifier: Development Status :: 5 - Production/Stable
Classifier: Intended Audience :: Developers
Classifier: License :: OSI Approved :: MIT License
Classifier: Programming Language :: Python :: 3
Classifier: Topic :: Communications
Classifier: Topic :: System :: Hardware :: Hardware Drivers
Requires-Python: >=3.8
